{
    "plugin": {
        "version": "4.8",
        "date": "Sat, 17 Oct 2020 16:11:00 +0000"
    },
    "groups": [
        {
            "id": 1,
            "name": "Redirections",
            "redirects": 0,
            "module_id": 1,
            "moduleName": "WordPress",
            "enabled": true
        },
        {
            "id": 2,
            "name": "Modified Posts",
            "redirects": 0,
            "module_id": 1,
            "moduleName": "WordPress",
            "enabled": true
        },
        {
            "id": 3,
            "name": "Redirections",
            "redirects": 4,
            "module_id": 1,
            "moduleName": "WordPress",
            "enabled": true
        },
        {
            "id": 4,
            "name": "Modified Posts",
            "redirects": 0,
            "module_id": 1,
            "moduleName": "WordPress",
            "enabled": true
        }
    ],
    "redirects": [
        {
            "id": 3,
            "url": "^/article/tag/(.*)",
            "match_url": "regex",
            "match_data": {
                "source": {
                    "flag_query": "exact",
                    "flag_case": false,
                    "flag_trailing": false,
                    "flag_regex": true
                }
            },
            "action_code": 301,
            "action_type": "url",
            "action_data": {
                "url": "/tag/$1"
            },
            "match_type": "url",
            "title": "",
            "hits": 3,
            "regex": true,
            "group_id": 3,
            "position": 0,
            "last_access": "October 2, 2020",
            "enabled": true
        },
        {
            "id": 4,
            "url": "/(.*) (.*)",
            "match_url": "/(.%2a)%20(.%2a)",
            "match_data": {
                "source": {
                    "flag_query": "exact",
                    "flag_case": false,
                    "flag_trailing": false,
                    "flag_regex": false
                }
            },
            "action_code": 301,
            "action_type": "url",
            "action_data": {
                "url": "/$1$2"
            },
            "match_type": "url",
            "title": "",
            "hits": 0,
            "regex": false,
            "group_id": 3,
            "position": 1,
            "last_access": "-",
            "enabled": true
        },
        {
            "id": 5,
            "url": "Featured image for new videos /",
            "match_url": "regex",
            "match_data": {
                "source": {
                    "flag_query": "exact",
                    "flag_case": false,
                    "flag_trailing": false,
                    "flag_regex": true
                }
            },
            "action_code": 301,
            "action_type": "url",
            "action_data": {
                "url": "Featured image for new videos_/"
            },
            "match_type": "url",
            "title": "",
            "hits": 2,
            "regex": true,
            "group_id": 3,
            "position": 2,
            "last_access": "October 1, 2020",
            "enabled": true
        },
        {
            "id": 6,
            "url": "/policy-edits/",
            "match_url": "/policy-edits",
            "match_data": {
                "source": {
                    "flag_query": "exact",
                    "flag_case": false,
                    "flag_trailing": false,
                    "flag_regex": false
                }
            },
            "action_code": 301,
            "action_type": "url",
            "action_data": {
                "url": "/article/category/policy-edits/"
            },
            "match_type": "url",
            "title": "",
            "hits": 1,
            "regex": false,
            "group_id": 3,
            "position": 3,
            "last_access": "October 17, 2020",
            "enabled": true
        }
    ]
}
